{
	"data":
	[
		{
			"name": "com_banners",
			"type": "component",
			"element": "com_banners",
			"folder": "",
			"client_id": 1,
			"enabled": 1,
			"access": 1,
			"protected": 0
		},
		{
			"name": "com_contact",
			"type": "component",
			"element": "com_contact",
			"folder": "",
			"client_id": 1,
			"enabled": 1,
			"access": 1,
			"protected": 0
		},
		{
			"name": "com_newsfeeds",
			"type": "component",
			"element": "com_newsfeeds",
			"folder": "",
			"client_id": 1,
			"enabled": 1,
			"access": 1,
			"protected": 0
		},
		{
			"name": "com_search",
			"type": "component",
			"element": "com_search",
			"folder": "",
			"client_id": 1,
			"enabled": 1,
			"access": 1,
			"protected": 0
		},
		{
			"name": "com_finder",
			"type": "component",
			"element": "com_finder",
			"folder": "",
			"client_id": 1,
			"enabled": 1,
			"access": 0,
			"protected": 0
		},
		{
			"name": "com_contenthistory",
			"type": "component",
			"element": "com_contenthistory",
			"folder": "",
			"client_id": 1,
			"enabled": 1,
			"access": 1,
			"protected": 0
		},
		{
			"name": "com_fields",
			"type": "component",
			"element": "com_fields",
			"folder": "",
			"client_id": 1,
			"enabled": 1,
			"access": 1,
			"protected": 0
		},
		{
			"name": "com_associations",
			"type": "component",
			"element": "com_associations",
			"folder": "",
			"client_id": 1,
			"enabled": 1,
			"access": 1,
			"protected": 0
		},
		{
			"name": "mod_articles_archive",
			"type": "module",
			"element": "mod_articles_archive",
			"folder": "",
			"client_id": 0,
			"enabled": 1,
			"access": 1,
			"protected": 0
		},
		{
			"name": "mod_articles_latest",
			"type": "module",
			"element": "mod_articles_latest",
			"folder": "",
			"client_id": 0,
			"enabled": 1,
			"access": 1,
			"protected": 0
		},
		{
			"name": "mod_articles_popular",
			"type": "module",
			"element": "mod_articles_popular",
			"folder": "",
			"client_id": 0,
			"enabled": 1,
			"access": 1,
			"protected": 0
		},
		{
			"name": "mod_banners",
			"type": "module",
			"element": "mod_banners",
			"folder": "",
			"client_id": 0,
			"enabled": 1,
			"access": 1,
			"protected": 0
		},
		{
			"name": "mod_feed",
			"type": "module",
			"element": "mod_feed",
			"folder": "",
			"client_id": 0,
			"enabled": 1,
			"access": 1,
			"protected": 0
		},
		{
			"name": "mod_footer",
			"type": "module",
			"element": "mod_footer",
			"folder": "",
			"client_id": 0,
			"enabled": 1,
			"access": 1,
			"protected": 0
		},
		{
			"name": "mod_articles_news",
			"type": "module",
			"element": "mod_articles_news",
			"folder": "",
			"client_id": 0,
			"enabled": 1,
			"access": 1,
			"protected": 0
		},
		{
			"name": "mod_random_image",
			"type": "module",
			"element": "mod_random_image",
			"folder": "",
			"client_id": 0,
			"enabled": 1,
			"access": 1,
			"protected": 0
		},
		{
			"name": "mod_related_items",
			"type": "module",
			"element": "mod_related_items",
			"folder": "",
			"client_id": 0,
			"enabled": 1,
			"access": 1,
			"protected": 0
		},
		{
			"name": "mod_search",
			"type": "module",
			"element": "mod_search",
			"folder": "",
			"client_id": 0,
			"enabled": 1,
			"access": 1,
			"protected": 0
		},
		{
			"name": "mod_stats",
			"type": "module",
			"element": "mod_stats",
			"folder": "",
			"client_id": 0,
			"enabled": 1,
			"access": 1,
			"protected": 0
		},
		{
			"name": "mod_users_latest",
			"type": "module",
			"element": "mod_users_latest",
			"folder": "",
			"client_id": 0,
			"enabled": 1,
			"access": 1,
			"protected": 0
		},
		{
			"name": "mod_whosonline",
			"type": "module",
			"element": "mod_whosonline",
			"folder": "",
			"client_id": 0,
			"enabled": 1,
			"access": 1,
			"protected": 0
		},
		{
			"name": "mod_wrapper",
			"type": "module",
			"element": "mod_wrapper",
			"folder": "",
			"client_id": 0,
			"enabled": 1,
			"access": 1,
			"protected": 0
		},
		{
			"name": "mod_articles_category",
			"type": "module",
			"element": "mod_articles_category",
			"folder": "",
			"client_id": 0,
			"enabled": 1,
			"access": 1,
			"protected": 0
		},
		{
			"name": "mod_articles_categories",
			"type": "module",
			"element": "mod_articles_categories",
			"folder": "",
			"client_id": 0,
			"enabled": 1,
			"access": 1,
			"protected": 0
		},
		{
			"name": "mod_finder",
			"type": "module",
			"element": "mod_finder",
			"folder": "",
			"client_id": 0,
			"enabled": 1,
			"access": 0,
			"protected": 0
		},
		{
			"name": "mod_feed",
			"type": "module",
			"element": "mod_feed",
			"folder": "",
			"client_id": 1,
			"enabled": 1,
			"access": 1,
			"protected": 0
		},
		{
			"name": "mod_latest",
			"type": "module",
			"element": "mod_latest",
			"folder": "",
			"client_id": 1,
			"enabled": 1,
			"access": 1,
			"protected": 0
		},
		{
			"name": "mod_logged",
			"type": "module",
			"element": "mod_logged",
			"folder": "",
			"client_id": 1,
			"enabled": 1,
			"access": 1,
			"protected": 0
		},
		{
			"name": "mod_menu",
			"type": "module",
			"element": "mod_menu",
			"folder": "",
			"client_id": 1,
			"enabled": 1,
			"access": 1,
			"protected": 0
		},
		{
			"name": "mod_popular",
			"type": "module",
			"element": "mod_popular",
			"folder": "",
			"client_id": 1,
			"enabled": 1,
			"access": 1,
			"protected": 0
		},
		{
			"name": "mod_status",
			"type": "module",
			"element": "mod_status",
			"folder": "",
			"client_id": 1,
			"enabled": 1,
			"access": 1,
			"protected": 0
		},
		{
			"name": "mod_submenu",
			"type": "module",
			"element": "mod_submenu",
			"folder": "",
			"client_id": 1,
			"enabled": 1,
			"access": 1,
			"protected": 0
		},
		{
			"name": "mod_title",
			"type": "module",
			"element": "mod_title",
			"folder": "",
			"client_id": 1,
			"enabled": 1,
			"access": 1,
			"protected": 0
		},
		{
			"name": "mod_multilangstatus",
			"type": "module",
			"element": "mod_multilangstatus",
			"folder": "",
			"client_id": 1,
			"enabled": 1,
			"access": 1,
			"protected": 0
		},
		{
			"name": "mod_version",
			"type": "module",
			"element": "mod_version",
			"folder": "",
			"client_id": 1,
			"enabled": 1,
			"access": 1,
			"protected": 0
		},
		{
			"name": "mod_stats_admin",
			"type": "module",
			"element": "mod_stats_admin",
			"folder": "",
			"client_id": 1,
			"enabled": 1,
			"access": 1,
			"protected": 0
		},
		{
			"name": "mod_tags_popular",
			"type": "module",
			"element": "mod_tags_popular",
			"folder": "",
			"client_id": 0,
			"enabled": 1,
			"access": 1,
			"protected": 0
		},
		{
			"name": "mod_tags_similar",
			"type": "module",
			"element": "mod_tags_similar",
			"folder": "",
			"client_id": 0,
			"enabled": 1,
			"access": 1,
			"protected": 0
		},
		{
			"name": "mod_sampledata",
			"type": "module",
			"element": "mod_sampledata",
			"folder": "",
			"client_id": 1,
			"enabled": 1,
			"access": 1,
			"protected": 0
		},
		{
			"name": "mod_latestactions",
			"type": "module",
			"element": "mod_latestactions",
			"folder": "",
			"client_id": 1,
			"enabled": 1,
			"access": 1,
			"protected": 0
		},
		{
			"name": "mod_privacy_dashboard",
			"type": "module",
			"element": "mod_privacy_dashboard",
			"folder": "",
			"client_id": 1,
			"enabled": 1,
			"access": 1,
			"protected": 0
		},
		{
			"name": "plg_authentication_gmail",
			"type": "plugin",
			"element": "gmail",
			"folder": "authentication",
			"client_id": 0,
			"enabled": 0,
			"access": 1,
			"protected": 0
		},
		{
			"name": "plg_authentication_ldap",
			"type": "plugin",
			"element": "ldap",
			"folder": "authentication",
			"client_id": 0,
			"enabled": 0,
			"access": 1,
			"protected": 0
		},
		{
			"name": "plg_content_contact",
			"type": "plugin",
			"element": "contact",
			"folder": "content",
			"client_id": 0,
			"enabled": 1,
			"access": 1,
			"protected": 0
		},
		{
			"name": "plg_content_emailcloak",
			"type": "plugin",
			"element": "emailcloak",
			"folder": "content",
			"client_id": 0,
			"enabled": 1,
			"access": 1,
			"protected": 0
		},
		{
			"name": "plg_content_loadmodule",
			"type": "plugin",
			"element": "loadmodule",
			"folder": "content",
			"client_id": 0,
			"enabled": 1,
			"access": 1,
			"protected": 0
		},
		{
			"name": "plg_content_pagebreak",
			"type": "plugin",
			"element": "pagebreak",
			"folder": "content",
			"client_id": 0,
			"enabled": 1,
			"access": 1,
			"protected": 0
		},
		{
			"name": "plg_content_pagenavigation",
			"type": "plugin",
			"element": "pagenavigation",
			"folder": "content",
			"client_id": 0,
			"enabled": 1,
			"access": 1,
			"protected": 0
		},
		{
			"name": "plg_content_vote",
			"type": "plugin",
			"element": "vote",
			"folder": "content",
			"client_id": 0,
			"enabled": 0,
			"access": 1,
			"protected": 0
		},
		{
			"name": "plg_editors_tinymce",
			"type": "plugin",
			"element": "tinymce",
			"folder": "editors",
			"client_id": 0,
			"enabled": 1,
			"access": 1,
			"protected": 0
		},
		{
			"name": "plg_editors-xtd_article",
			"type": "plugin",
			"element": "article",
			"folder": "editors-xtd",
			"client_id": 0,
			"enabled": 1,
			"access": 1,
			"protected": 0
		},
		{
			"name": "plg_editors-xtd_image",
			"type": "plugin",
			"element": "image",
			"folder": "editors-xtd",
			"client_id": 0,
			"enabled": 1,
			"access": 1,
			"protected": 0
		},
		{
			"name": "plg_editors-xtd_pagebreak",
			"type": "plugin",
			"element": "pagebreak",
			"folder": "editors-xtd",
			"client_id": 0,
			"enabled": 1,
			"access": 1,
			"protected": 0
		},
		{
			"name": "plg_editors-xtd_readmore",
			"type": "plugin",
			"element": "readmore",
			"folder": "editors-xtd",
			"client_id": 0,
			"enabled": 1,
			"access": 1,
			"protected": 0
		},
		{
			"name": "plg_search_categories",
			"type": "plugin",
			"element": "categories",
			"folder": "search",
			"client_id": 0,
			"enabled": 1,
			"access": 1,
			"protected": 0
		},
		{
			"name": "plg_search_contacts",
			"type": "plugin",
			"element": "contacts",
			"folder": "search",
			"client_id": 0,
			"enabled": 1,
			"access": 1,
			"protected": 0
		},
		{
			"name": "plg_search_content",
			"type": "plugin",
			"element": "content",
			"folder": "search",
			"client_id": 0,
			"enabled": 1,
			"access": 1,
			"protected": 0
		},
		{
			"name": "plg_search_newsfeeds",
			"type": "plugin",
			"element": "newsfeeds",
			"folder": "search",
			"client_id": 0,
			"enabled": 1,
			"access": 1,
			"protected": 0
		},
		{
			"name": "plg_system_p3p",
			"type": "plugin",
			"element": "p3p",
			"folder": "system",
			"client_id": 0,
			"enabled": 0,
			"access": 1,
			"protected": 0
		},
		{
			"name": "plg_system_debug",
			"type": "plugin",
			"element": "debug",
			"folder": "system",
			"client_id": 0,
			"enabled": 1,
			"access": 1,
			"protected": 0
		},
		{
			"name": "plg_system_sef",
			"type": "plugin",
			"element": "sef",
			"folder": "system",
			"client_id": 0,
			"enabled": 1,
			"access": 1,
			"protected": 0
		},
		{
			"name": "plg_user_contactcreator",
			"type": "plugin",
			"element": "contactcreator",
			"folder": "user",
			"client_id": 0,
			"enabled": 0,
			"access": 1,
			"protected": 0
		},
		{
			"name": "plg_user_joomla",
			"type": "plugin",
			"element": "joomla",
			"folder": "user",
			"client_id": 0,
			"enabled": 1,
			"access": 1,
			"protected": 0
		},
		{
			"name": "plg_user_profile",
			"type": "plugin",
			"element": "profile",
			"folder": "user",
			"client_id": 0,
			"enabled": 0,
			"access": 1,
			"protected": 0
		},
		{
			"name": "plg_content_joomla",
			"type": "plugin",
			"element": "joomla",
			"folder": "content",
			"client_id": 0,
			"enabled": 1,
			"access": 1,
			"protected": 0
		},
		{
			"name": "plg_system_languagecode",
			"type": "plugin",
			"element": "languagecode",
			"folder": "system",
			"client_id": 0,
			"enabled": 0,
			"access": 1,
			"protected": 0
		},
		{
			"name": "plg_captcha_recaptcha",
			"type": "plugin",
			"element": "recaptcha",
			"folder": "captcha",
			"client_id": 0,
			"enabled": 0,
			"access": 1,
			"protected": 0
		},
		{
			"name": "plg_system_highlight",
			"type": "plugin",
			"element": "highlight",
			"folder": "system",
			"client_id": 0,
			"enabled": 1,
			"access": 1,
			"protected": 0
		},
		{
			"name": "plg_content_finder",
			"type": "plugin",
			"element": "finder",
			"folder": "content",
			"client_id": 0,
			"enabled": 0,
			"access": 1,
			"protected": 0
		},
		{
			"name": "plg_finder_categories",
			"type": "plugin",
			"element": "categories",
			"folder": "finder",
			"client_id": 0,
			"enabled": 1,
			"access": 1,
			"protected": 0
		},
		{
			"name": "plg_finder_contacts",
			"type": "plugin",
			"element": "contacts",
			"folder": "finder",
			"client_id": 0,
			"enabled": 1,
			"access": 1,
			"protected": 0
		},
		{
			"name": "plg_finder_content",
			"type": "plugin",
			"element": "content",
			"folder": "finder",
			"client_id": 0,
			"enabled": 1,
			"access": 1,
			"protected": 0
		},
		{
			"name": "plg_finder_newsfeeds",
			"type": "plugin",
			"element": "newsfeeds",
			"folder": "finder",
			"client_id": 0,
			"enabled": 1,
			"access": 1,
			"protected": 0
		},
		{
			"name": "plg_finder_tags",
			"type": "plugin",
			"element": "tags",
			"folder": "finder",
			"client_id": 0,
			"enabled": 1,
			"access": 1,
			"protected": 0
		},
		{
			"name": "plg_twofactorauth_totp",
			"type": "plugin",
			"element": "totp",
			"folder": "twofactorauth",
			"client_id": 0,
			"enabled": 0,
			"access": 1,
			"protected": 0
		},
		{
			"name": "plg_authentication_cookie",
			"type": "plugin",
			"element": "cookie",
			"folder": "authentication",
			"client_id": 0,
			"enabled": 1,
			"access": 1,
			"protected": 0
		},
		{
			"name": "plg_twofactorauth_yubikey",
			"type": "plugin",
			"element": "yubikey",
			"folder": "twofactorauth",
			"client_id": 0,
			"enabled": 0,
			"access": 1,
			"protected": 0
		},
		{
			"name": "plg_search_tags",
			"type": "plugin",
			"element": "tags",
			"folder": "search",
			"client_id": 0,
			"enabled": 1,
			"access": 1,
			"protected": 0
		},
		{
			"name": "plg_system_updatenotification",
			"type": "plugin",
			"element": "updatenotification",
			"folder": "system",
			"client_id": 0,
			"enabled": 1,
			"access": 1,
			"protected": 0
		},
		{
			"name": "plg_editors-xtd_module",
			"type": "plugin",
			"element": "module",
			"folder": "editors-xtd",
			"client_id": 0,
			"enabled": 1,
			"access": 1,
			"protected": 0
		},
		{
			"name": "plg_system_stats",
			"type": "plugin",
			"element": "stats",
			"folder": "system",
			"client_id": 0,
			"enabled": 1,
			"access": 1,
			"protected": 0
		},
		{
			"name": "plg_editors-xtd_menu",
			"type": "plugin",
			"element": "menu",
			"folder": "editors-xtd",
			"client_id": 0,
			"enabled": 1,
			"access": 1,
			"protected": 0
		},
		{
			"name": "plg_editors-xtd_contact",
			"type": "plugin",
			"element": "contact",
			"folder": "editors-xtd",
			"client_id": 0,
			"enabled": 1,
			"access": 1,
			"protected": 0
		},
		{
			"name": "plg_system_fields",
			"type": "plugin",
			"element": "fields",
			"folder": "system",
			"client_id": 0,
			"enabled": 1,
			"access": 1,
			"protected": 0
		},
		{
			"name": "plg_fields_calendar",
			"type": "plugin",
			"element": "calendar",
			"folder": "fields",
			"client_id": 0,
			"enabled": 1,
			"access": 1,
			"protected": 0
		},
		{
			"name": "plg_fields_checkboxes",
			"type": "plugin",
			"element": "checkboxes",
			"folder": "fields",
			"client_id": 0,
			"enabled": 1,
			"access": 1,
			"protected": 0
		},
		{
			"name": "plg_fields_color",
			"type": "plugin",
			"element": "color",
			"folder": "fields",
			"client_id": 0,
			"enabled": 1,
			"access": 1,
			"protected": 0
		},
		{
			"name": "plg_fields_editor",
			"type": "plugin",
			"element": "editor",
			"folder": "fields",
			"client_id": 0,
			"enabled": 1,
			"access": 1,
			"protected": 0
		},
		{
			"name": "plg_fields_imagelist",
			"type": "plugin",
			"element": "imagelist",
			"folder": "fields",
			"client_id": 0,
			"enabled": 1,
			"access": 1,
			"protected": 0
		},
		{
			"name": "plg_fields_integer",
			"type": "plugin",
			"element": "integer",
			"folder": "fields",
			"client_id": 0,
			"enabled": 1,
			"access": 1,
			"protected": 0
		},
		{
			"name": "plg_fields_list",
			"type": "plugin",
			"element": "list",
			"folder": "fields",
			"client_id": 0,
			"enabled": 1,
			"access": 1,
			"protected": 0
		},
		{
			"name": "plg_fields_media",
			"type": "plugin",
			"element": "media",
			"folder": "fields",
			"client_id": 0,
			"enabled": 1,
			"access": 1,
			"protected": 0
		},
		{
			"name": "plg_fields_radio",
			"type": "plugin",
			"element": "radio",
			"folder": "fields",
			"client_id": 0,
			"enabled": 1,
			"access": 1,
			"protected": 0
		},
		{
			"name": "plg_fields_sql",
			"type": "plugin",
			"element": "sql",
			"folder": "fields",
			"client_id": 0,
			"enabled": 1,
			"access": 1,
			"protected": 0
		},
		{
			"name": "plg_fields_text",
			"type": "plugin",
			"element": "text",
			"folder": "fields",
			"client_id": 0,
			"enabled": 1,
			"access": 1,
			"protected": 0
		},
		{
			"name": "plg_fields_textarea",
			"type": "plugin",
			"element": "textarea",
			"folder": "fields",
			"client_id": 0,
			"enabled": 1,
			"access": 1,
			"protected": 0
		},
		{
			"name": "plg_fields_url",
			"type": "plugin",
			"element": "url",
			"folder": "fields",
			"client_id": 0,
			"enabled": 1,
			"access": 1,
			"protected": 0
		},
		{
			"name": "plg_fields_user",
			"type": "plugin",
			"element": "user",
			"folder": "fields",
			"client_id": 0,
			"enabled": 1,
			"access": 1,
			"protected": 0
		},
		{
			"name": "plg_fields_usergrouplist",
			"type": "plugin",
			"element": "usergrouplist",
			"folder": "fields",
			"client_id": 0,
			"enabled": 1,
			"access": 1,
			"protected": 0
		},
		{
			"name": "plg_content_fields",
			"type": "plugin",
			"element": "fields",
			"folder": "content",
			"client_id": 0,
			"enabled": 1,
			"access": 1,
			"protected": 0
		},
		{
			"name": "plg_editors-xtd_fields",
			"type": "plugin",
			"element": "fields",
			"folder": "editors-xtd",
			"client_id": 0,
			"enabled": 1,
			"access": 1,
			"protected": 0
		},
		{
			"name": "plg_sampledata_blog",
			"type": "plugin",
			"element": "blog",
			"folder": "sampledata",
			"client_id": 0,
			"enabled": 1,
			"access": 1,
			"protected": 0
		},
		{
			"name": "plg_system_sessiongc",
			"type": "plugin",
			"element": "sessiongc",
			"folder": "system",
			"client_id": 0,
			"enabled": 1,
			"access": 1,
			"protected": 0
		},
		{
			"name": "plg_fields_repeatable",
			"type": "plugin",
			"element": "repeatable",
			"folder": "fields",
			"client_id": 0,
			"enabled": 1,
			"access": 1,
			"protected": 0
		},
    {
			"name": "plg_content_confirmconsent",
			"type": "plugin",
			"element": "confirmconsent",
			"folder": "content",
			"client_id": 0,
			"enabled": 0,
			"access": 1,
			"protected": 0
		},
		{
			"name": "PLG_SYSTEM_ACTIONLOGS",
			"type": "plugin",
			"element": "actionlogs",
			"folder": "system",
			"client_id": 0,
			"enabled": 1,
			"access": 1,
			"protected": 0
		},
		{
			"name": "PLG_ACTIONLOG_JOOMLA",
			"type": "plugin",
			"element": "joomla",
			"folder": "actionlog",
			"client_id": 0,
			"enabled": 1,
			"access": 1,
			"protected": 0
		},
		{
			"name": "plg_system_privacyconsent",
			"type": "plugin",
			"element": "privacyconsent",
			"folder": "system",
			"client_id": 0,
			"enabled": 0,
			"access": 1,
			"protected": 0
		},
		{
			"name": "plg_system_logrotation",
			"type": "plugin",
			"element": "logrotation",
			"folder": "system",
			"client_id": 0,
			"enabled": 1,
			"access": 1,
			"protected": 0
		},
		{
			"name": "plg_privacy_user",
			"type": "plugin",
			"element": "user",
			"folder": "privacy",
			"client_id": 0,
			"enabled": 1,
			"access": 1,
			"protected": 0
		},
		{
			"name": "plg_quickicon_privacycheck",
			"type": "plugin",
			"element": "privacycheck",
			"folder": "quickicon",
			"client_id": 0,
			"enabled": 1,
			"access": 1,
			"protected": 0
		},
		{
			"name": "plg_user_terms",
			"type": "plugin",
			"element": "terms",
			"folder": "user",
			"client_id": 0,
			"enabled": 0,
			"access": 1,
			"protected": 0
		},
		{
			"name": "plg_privacy_contact",
			"type": "plugin",
			"element": "contact",
			"folder": "privacy",
			"client_id": 0,
			"enabled": 1,
			"access": 1,
			"protected": 0
		},
		{
			"name": "plg_privacy_content",
			"type": "plugin",
			"element": "content",
			"folder": "privacy",
			"client_id": 0,
			"enabled": 1,
			"access": 1,
			"protected": 0
		},
		{
			"name": "plg_privacy_message",
			"type": "plugin",
			"element": "message",
			"folder": "privacy",
			"client_id": 0,
			"enabled": 1,
			"access": 1,
			"protected": 0
		},
		{
			"name": "plg_privacy_actionlogs",
			"type": "plugin",
			"element": "actionlogs",
			"folder": "privacy",
			"client_id": 0,
			"enabled": 1,
			"access": 1,
			"protected": 0
		},
		{
			"name": "plg_captcha_recaptcha_invisible",
			"type": "plugin",
			"element": "recaptcha_invisible",
			"folder": "captcha",
			"client_id": 0,
			"enabled": 0,
			"access": 1,
			"protected": 0
		},
		{
			"name": "plg_privacy_consents",
			"type": "plugin",
			"element": "consents",
			"folder": "privacy",
			"client_id": 0,
			"enabled": 1,
			"access": 1,
			"protected": 0
		},
		{
			"name": "beez3",
			"type": "template",
			"element": "beez3",
			"folder": "",
			"client_id": 0,
			"enabled": 1,
			"access": 1,
			"protected": 0
		},
		{
			"name": "hathor",
			"type": "template",
			"element": "hathor",
			"folder": "",
			"client_id": 1,
			"enabled": 1,
			"access": 1,
			"protected": 0
		},
		{
			"name": "protostar",
			"type": "template",
			"element": "protostar",
			"folder": "",
			"client_id": 0,
			"enabled": 1,
			"access": 1,
			"protected": 0
		},
		{
			"name": "isis",
			"type": "template",
			"element": "isis",
			"folder": "",
			"client_id": 1,
			"enabled": 1,
			"access": 1,
			"protected": 0
		}
	]
}